lungdata/__init__.py
lungdata/augment.py
lungdata/cli.py
lungdata/dataset.py
lungdata/features.py
lungdata/path.py
lungdata/records.py
lungdata/utils.py
lungdata/meta/ICBHI_Challenge_diagnosis.txt
lungdata/meta/README.md
lungdata/meta/demographic_info.txt
lungdata-0.1.3.dist-info/METADATA
lungdata-0.1.3.dist-info/WHEEL
lungdata-0.1.3.dist-info/entry_points.txt
lungdata-0.1.3.dist-info/top_level.txt
lungdata-0.1.3.dist-info/RECORD
