Metadata-Version: 2.1
Name: lungdata
Version: 0.1.3
Author: Glenn
Author-email: gward@python.net
Requires-Dist: numpy
Requires-Dist: librosa
Requires-Dist: pandas
Requires-Dist: soundfile
Requires-Dist: toml
Requires-Dist: audiomentations
